anime_quiz/__init__.py
anime_quiz/asgi.py
anime_quiz/settings.py
anime_quiz/settings_gcp.py
anime_quiz/settings_prod.py
anime_quiz/urls.py
anime_quiz/wsgi.py
quiz/.DS_Store
quiz/__init__.py
quiz/animethemes.py
quiz/apps.py
quiz/gcp.py
quiz/mal.py
quiz/tasks.py
quiz/tests.py
quiz/urls.py
quiz/views.py
quiz/migrations/__init__.py
quiz/static/.DS_Store
quiz/static/quiz/favicon.ico
quiz/static/quiz/main.css
quiz/static/quiz/main.js
quiz/static/quiz/rem-ram.gif
quiz/templates/quiz/quiz.html
quiz/templates/quiz/results_template.html
quiz/templates/quiz/robots.txt
quiz/templates/quiz/username.html
anime_quiz-1.0.dist-info/COPYING
anime_quiz-1.0.dist-info/METADATA
anime_quiz-1.0.dist-info/WHEEL
anime_quiz-1.0.dist-info/entry_points.txt
anime_quiz-1.0.dist-info/top_level.txt
anime_quiz-1.0.dist-info/RECORD
