Metadata-Version: 2.1
Name: anime_quiz
Version: 1.0
Summary: Anime Themes Quiz for people with taste.
Author-email: Przemysław Buczkowski <prem@prem.moe>
Project-URL: Homepage, https://quiz.moe
Project-URL: Repository, https://github.com/przemub/anime_quiz
Classifier: Development Status :: 4 - Beta
Classifier: Framework :: Django
Classifier: Intended Audience :: End Users/Desktop
Classifier: License :: OSI Approved :: GNU Affero General Public License v3
Classifier: Programming Language :: Python :: 3 :: Only
Classifier: Topic :: Games/Entertainment
Classifier: Topic :: Internet :: WWW/HTTP :: Dynamic Content
Classifier: Topic :: Multimedia :: Video :: Display
Requires-Python: >=3.8
License-File: COPYING
Requires-Dist: animelyrics==0.1.0
Requires-Dist: bugsnag~=4.7.1
Requires-Dist: Django~=5.1.3
Requires-Dist: django-redis~=5.4.0
Requires-Dist: first==2.0.2
Requires-Dist: redis[hiredis]~=5.2.0
Requires-Dist: requests~=2.32.3
Requires-Dist: uWSGI~=2.0.28
Provides-Extra: dev
Requires-Dist: build==1.2.2.post1; extra == "dev"
Requires-Dist: black==24.10.0; extra == "dev"
Provides-Extra: gcp
Requires-Dist: django-google-cloud-tasks~=2.17.0; extra == "gcp"
Requires-Dist: google-cloud-logging; extra == "gcp"
Provides-Extra: opentelemetry
Requires-Dist: aws-opentelemetry-distro; extra == "opentelemetry"
Requires-Dist: opentelemetry-instrumentation-django; extra == "opentelemetry"
Requires-Dist: opentelemetry-instrumentation-requests; extra == "opentelemetry"
Requires-Dist: opentelemetry-instrumentation-redis; extra == "opentelemetry"
